arguments.py
compilation_database.py
index.py
logger.py
properties_parser.py
data/__init__.py
data/c_cpp_properties.py
data/compilation_database.py
cpp_to_compile_commands-0.1.1.dist-info/METADATA
cpp_to_compile_commands-0.1.1.dist-info/WHEEL
cpp_to_compile_commands-0.1.1.dist-info/entry_points.txt
cpp_to_compile_commands-0.1.1.dist-info/top_level.txt
cpp_to_compile_commands-0.1.1.dist-info/RECORD
