Metadata-Version: 2.4
Name: cpp-to-compile-commands
Version: 0.1.1
Summary: Convert microsoft c_cpp_properties.json to a compilation database file
Author: Totto16
License-Expression: MIT
Requires-Python: >=3.10
Requires-Dist: pydantic>=2.11.5
